{
    "series": "Uncanny X-Men, Vol. 1",
    "issue_number": "199",
    "issue_ext": "A",
    "publisher": "Marvel Comics",
    "cover_date": "1985/11",
    "purchase_date": null,
    "value": "4.00",
    "cover_url": "https://clzcomics.r.sizr.io/core/covers/lg/3b/3b_94632_0_UncannyXMenVol1199A.jpg",
    "collection_status": "On Wish List",
    "age": "Modern",
    "key": "Minor",
    "key_reason": "1st app. Phoenix (Rachel Summers)",
    "datasetversion": "12",
    "hash": "CLZ-0000",
    "bpcomicid": "94632",
    "title": "The Spiral Path",
    "bpseriesid": "8106",
    "displayname": "1st appearance",
    "complete": "No",
    "onpulllist": "No",
    "ignoreformissingcomics": "No",
    "pagecount": "32",
    "myrating": "0",
    "issuenr": "199",
    "issueext": "A",
    "month": "11",
    "date": "1985/11",
    "displaydate": "Nov 1985",
    "day": "06",
    "timestamp": "1711322296",
    "coverfrontdefault": "https://clzcomics.r.sizr.io/core/covers/lg/3b/3b_94632_0_UncannyXMenVol1199A.jpg",
    "coverfrontfilesizedefault": "-1",
    "quantity": "1",
    "index": "1390",
    "collectionstatus": "On Wish List",
    "currentprice": "0",
    "coverprice": "0.65",
    "readit": "No",
    "sortid": "0",
    "iskeycomic": "Minor",
    "keycomicreason": "1st app. Phoenix (Rachel Summers)",
    "valueislocked": "No",
    "id": "376124",
    "rating": "0.0",
    "isslabbed": "Raw",
    "grade": "FN",
    "raw": "1",
    "stale": "0",
    "usecustomcreators": "No",
    "usecustomcharacters": "No"
}