{
    "series": "The Spectacular Spider-Man, Vol. 1",
    "issue_number": "262",
    "issue_ext": "A",
    "publisher": "Marvel Comics",
    "cover_date": "1998/10",
    "purchase_date": null,
    "value": "3.00",
    "cover_url": "https://clzcomics.r.sizr.io/core/covers/lg/80/80_79954_0_Part4ADayintheLife.jpg",
    "collection_status": "Not in Collection",
    "age": "Modern",
    "key": "Minor",
    "key_reason": "1st cameo app. Martha \"Mattie\" Franklin",
    "datasetversion": "12",
    "hash": "CLZ-0000",
    "bpcomicid": "79954",
    "title": "Part 4: A Day in the Life",
    "bpseriesid": "9643",
    "displayname": "1st/2nd/3rd cameo appearance",
    "lastname": "Spectacular Spider-Man, Vol. 1",
    "the": "The",
    "sortname": "Spectacular Spider-Man, Vol. 1, The",
    "complete": "No",
    "onpulllist": "No",
    "ignoreformissingcomics": "No",
    "pagecount": "32",
    "myrating": "0",
    "issuenr": "262",
    "issueext": "A",
    "month": "10",
    "date": "1998/10",
    "displaydate": "Oct 1998",
    "day": "26",
    "timestamp": "1712097226",
    "barcode": "75960602199426211",
    "coverfrontdefault": "https://clzcomics.r.sizr.io/core/covers/lg/80/80_79954_0_Part4ADayintheLife.jpg",
    "coverfrontfilesizedefault": "-1",
    "quantity": "1",
    "index": "2300",
    "collectionstatus": "Not in Collection",
    "currentprice": "0",
    "coverprice": "1.99",
    "readit": "No",
    "sortid": "0",
    "iskeycomic": "Minor",
    "keycomicreason": "1st cameo app. Martha \"Mattie\" Franklin",
    "valueislocked": "No",
    "id": "159918",
    "rating": "0.0",
    "isslabbed": "Raw",
    "grade": "VF",
    "raw": "1",
    "stale": "0",
    "usecustomcreators": "No",
    "usecustomcharacters": "No"
}