{
    "series": "The Amazing Spider-Man, Vol. 1",
    "issue_number": "329",
    "issue_ext": "B",
    "publisher": "Marvel Comics",
    "cover_date": "1990/02",
    "purchase_date": "2024/01/18",
    "value": "7.00",
    "cover_url": "https://clzcomics.r.sizr.io/core/covers/lg/1f/1f_744857_0_PowerPrey.jpg",
    "collection_status": "In Collection",
    "age": "Modern",
    "key": "Minor",
    "key_reason": "1st app. Tri-Sentinel, Debut of Spider-Man\u2019s Captain Universe suit",
    "datasetversion": "12",
    "hash": "CLZ-0000",
    "bpcomicid": "744857",
    "title": "Power Prey!",
    "bpseriesid": "705",
    "displayname": "New costume",
    "lastname": "Amazing Spider-Man",
    "the": "Vol. 1",
    "sortname": "Amazing Spider-Man, Vol. 1",
    "complete": "No",
    "onpulllist": "Yes",
    "ignoreformissingcomics": "No",
    "pagecount": "32",
    "myrating": "0",
    "issuenr": "329",
    "issueext": "B",
    "month": "01",
    "date": "2024/01/18",
    "displaydate": "Jan 18, 2024",
    "day": "18",
    "timestamp": "1706748375",
    "barcode": "07148602457602",
    "coverfrontdefault": "https://clzcomics.r.sizr.io/core/covers/lg/1f/1f_744857_0_PowerPrey.jpg",
    "coverfrontfilesizedefault": "-1",
    "quantity": "1",
    "index": "789",
    "collectionstatus": "In Collection",
    "currentprice": "0",
    "purchaseprice": "5.00",
    "readit": "No",
    "sortid": "0",
    "iskeycomic": "Minor",
    "keycomicreason": "1st app. Tri-Sentinel, Debut of Spider-Man\u2019s Captain Universe suit",
    "valueislocked": "No",
    "id": "14477",
    "rating": "0.0",
    "isslabbed": "Raw",
    "grade": "FN",
    "raw": "1",
    "stale": "0",
    "usecustomcreators": "No",
    "usecustomcharacters": "No"
}