{
    "series": "The Amazing Spider-Man, Vol. 2",
    "issue_number": "628",
    "issue_ext": "A",
    "publisher": "Marvel Comics",
    "cover_date": "2010/06",
    "purchase_date": "2024/01/18",
    "value": "4.00",
    "cover_url": "https://clzcomics.r.sizr.io/core/covers/lg/71/71_238559_0_VengeanceIsMine.jpg",
    "collection_status": "In Collection",
    "age": "Modern",
    "key": "No",
    "key_reason": null,
    "datasetversion": "12",
    "hash": "CLZ-0000",
    "bpcomicid": "238559",
    "title": "Vengeance Is Mine!",
    "bpseriesid": "11511",
    "displayname": "Super-Heroes",
    "lastname": "Amazing Spider-Man",
    "the": "Vol. 2",
    "sortname": "Amazing Spider-Man, Vol. 2",
    "complete": "No",
    "onpulllist": "No",
    "ignoreformissingcomics": "No",
    "pagecount": "40",
    "myrating": "0",
    "issuenr": "628",
    "issueext": "A",
    "month": "01",
    "date": "2024/01/18",
    "displaydate": "Jan 18, 2024",
    "day": "18",
    "timestamp": "1705627687",
    "barcode": "00928103503905",
    "coverfrontdefault": "https://clzcomics.r.sizr.io/core/covers/lg/71/71_238559_0_VengeanceIsMine.jpg",
    "coverfrontfilesizedefault": "-1",
    "quantity": "1",
    "index": "799",
    "collectionstatus": "In Collection",
    "currentprice": "0",
    "coverprice": "3.99",
    "purchaseprice": "2.00",
    "readit": "No",
    "sortid": "0",
    "iskeycomic": "No",
    "valueislocked": "No",
    "id": "21169",
    "rating": "0.0",
    "isslabbed": "Raw",
    "grade": "VF",
    "raw": "1",
    "stale": "0",
    "usecustomcreators": "No",
    "usecustomcharacters": "No"
}