{
    "series": "The Amazing Spider-Man, Vol. 2",
    "issue_number": "8",
    "issue_ext": "A/449",
    "publisher": "Marvel Comics",
    "cover_date": "1999/08",
    "purchase_date": "2024/02/10",
    "value": "7.00",
    "cover_url": "https://clzcomics.r.sizr.io/core/covers/lg/10/10_8396_0_AmazingSpiderManVol28ThePerfec.jpg",
    "collection_status": "In Collection",
    "age": "Modern",
    "key": "No",
    "key_reason": null,
    "datasetversion": "12",
    "hash": "CLZ-0000",
    "bpcomicid": "8396",
    "title": "Part 2: The Man Behind the Curtain",
    "bpseriesid": "11511",
    "displayname": "Super-Heroes",
    "lastname": "Amazing Spider-Man",
    "the": "Vol. 2",
    "sortname": "Amazing Spider-Man, Vol. 2",
    "complete": "No",
    "onpulllist": "No",
    "ignoreformissingcomics": "No",
    "pagecount": "32",
    "myrating": "0",
    "issuenr": "8",
    "issueext": "A/449",
    "month": "02",
    "date": "2024/02/10",
    "displaydate": "Feb 10, 2024",
    "timestamp": "1707593603",
    "barcode": "75960604716100811",
    "coverfrontdefault": "https://clzcomics.r.sizr.io/core/covers/lg/10/10_8396_0_AmazingSpiderManVol28ThePerfec.jpg",
    "coverfrontfilesizedefault": "-1",
    "quantity": "1",
    "index": "948",
    "collectionstatus": "In Collection",
    "currentprice": "0",
    "coverprice": "1.99",
    "purchaseprice": "6.00",
    "day": "10",
    "readit": "No",
    "sortid": "0",
    "iskeycomic": "No",
    "valueislocked": "No",
    "id": "164312",
    "rating": "0.0",
    "isslabbed": "Raw",
    "grade": "VF",
    "raw": "1",
    "stale": "0",
    "usecustomcreators": "No",
    "usecustomcharacters": "No"
}