{
    "series": "The Amazing Spider-Man, Vol. 1",
    "issue_number": "278",
    "issue_ext": "A",
    "publisher": "Marvel Comics",
    "cover_date": "1986/07",
    "purchase_date": "2024/01/07",
    "value": "12.00",
    "cover_url": "https://clzcomics.r.sizr.io/core/covers/lg/eb/eb_712147_0_SpideySavesFlashDeathOfTheWrai.jpg",
    "collection_status": "In Collection",
    "age": "Modern",
    "key": "Minor",
    "key_reason": "Death of Wraith",
    "datasetversion": "12",
    "hash": "CLZ-0000",
    "bpcomicid": "712147",
    "title": "Spidey Saves Flash, Death Of The Wraith/Scourge",
    "bpseriesid": "705",
    "displayname": "Death",
    "lastname": "Amazing Spider-Man",
    "the": "Vol. 1",
    "sortname": "Amazing Spider-Man, Vol. 1",
    "complete": "No",
    "onpulllist": "Yes",
    "ignoreformissingcomics": "No",
    "pagecount": "32",
    "myrating": "0",
    "issuenr": "278",
    "issueext": "A",
    "month": "01",
    "date": "2024/01/07",
    "displaydate": "Jan 07, 2024",
    "timestamp": "1707196269",
    "coverfrontdefault": "https://clzcomics.r.sizr.io/core/covers/lg/eb/eb_712147_0_SpideySavesFlashDeathOfTheWrai.jpg",
    "coverfrontfilesizedefault": "-1",
    "quantity": "1",
    "index": "686",
    "collectionstatus": "In Collection",
    "currentprice": "0",
    "purchaseprice": "2.97",
    "day": "07",
    "readit": "No",
    "sortid": "0",
    "iskeycomic": "Minor",
    "keycomicreason": "Death of Wraith",
    "valueislocked": "No",
    "id": "379450",
    "rating": "0.0",
    "isslabbed": "Raw",
    "grade": "VF",
    "raw": "1",
    "stale": "0",
    "usecustomcreators": "No",
    "usecustomcharacters": "No"
}