{
    "series": "The Amazing Spider-Man, Vol. 1",
    "issue_number": "100",
    "issue_ext": "A",
    "publisher": "Marvel Comics",
    "cover_date": "1971/09",
    "purchase_date": "2024/02/13",
    "value": "87.00",
    "cover_url": "https://clzcomics.r.sizr.io/core/covers/lg/60/60_7937_0_TheSpiderortheMan.jpg",
    "collection_status": "In Collection",
    "age": "Bronze",
    "key": "Major",
    "key_reason": "100th anniversary issue",
    "datasetversion": "12",
    "hash": "CLZ-0000",
    "bpcomicid": "7937",
    "title": "The Spider or the Man?",
    "bpseriesid": "705",
    "displayname": "First/Last/Nth issue",
    "lastname": "Amazing Spider-Man",
    "the": "Vol. 1",
    "sortname": "Amazing Spider-Man, Vol. 1",
    "complete": "No",
    "onpulllist": "Yes",
    "ignoreformissingcomics": "No",
    "pagecount": "32",
    "myrating": "0",
    "issuenr": "100",
    "issueext": "A",
    "month": "02",
    "date": "2024/02/13",
    "displaydate": "Feb 13, 2024",
    "timestamp": "1710442274",
    "coverfrontdefault": "https://clzcomics.r.sizr.io/core/covers/lg/60/60_7937_0_TheSpiderortheMan.jpg",
    "coverfrontfilesizedefault": "-1",
    "quantity": "1",
    "index": "83",
    "collectionstatus": "In Collection",
    "currentprice": "0",
    "coverprice": "0.15",
    "purchaseprice": "80.38",
    "day": "13",
    "readit": "No",
    "sortid": "0",
    "iskeycomic": "Major",
    "keycomicreason": "100th anniversary issue",
    "valueislocked": "No",
    "id": "320366",
    "rating": "0.0",
    "isslabbed": "Raw",
    "grade": "VG",
    "raw": "1",
    "stale": "0",
    "usecustomcreators": "No",
    "usecustomcharacters": "No"
}