{
    "series": "The Amazing Spider-Man, Vol. 3",
    "issue_number": "13",
    "issue_ext": "A",
    "publisher": "Marvel Comics",
    "cover_date": "2015/03",
    "purchase_date": null,
    "value": "7.00",
    "cover_url": "https://clzcomics.r.sizr.io/core/covers/lg/62/62_387845_0_PartFiveSpiderMenNoMore.jpg",
    "collection_status": "On Wish List",
    "age": "Modern",
    "key": "No",
    "key_reason": null,
    "datasetversion": "12",
    "hash": "CLZ-0000",
    "bpcomicid": "387845",
    "title": "Part Five: Spider-Men: No More",
    "bpseriesid": "54411",
    "displayname": "Super-Heroes",
    "lastname": "Amazing Spider-Man",
    "the": "Vol. 3",
    "sortname": "Amazing Spider-Man, Vol. 3",
    "complete": "No",
    "onpulllist": "No",
    "ignoreformissingcomics": "No",
    "pagecount": "28",
    "myrating": "0",
    "issuenr": "13",
    "issueext": "A",
    "month": "03",
    "date": "2015/03",
    "displaydate": "Mar 2015",
    "day": "21",
    "timestamp": "1706326877",
    "barcode": "75960607901801311",
    "coverfrontdefault": "https://clzcomics.r.sizr.io/core/covers/lg/62/62_387845_0_PartFiveSpiderMenNoMore.jpg",
    "coverfrontfilesizedefault": "-1",
    "quantity": "1",
    "index": "391",
    "collectionstatus": "On Wish List",
    "currentprice": "0",
    "coverprice": "3.99",
    "readit": "No",
    "sortid": "0",
    "iskeycomic": "No",
    "valueislocked": "No",
    "id": "75052",
    "rating": "0.0",
    "isslabbed": "Raw",
    "grade": "NM",
    "raw": "1",
    "stale": "0",
    "usecustomcreators": "No",
    "usecustomcharacters": "No"
}